cvxlab/__init__.py
cvxlab/defaults.py
cvxlab/backend/__init__.py
cvxlab/backend/core.py
cvxlab/backend/data_table.py
cvxlab/backend/database.py
cvxlab/backend/index.py
cvxlab/backend/model.py
cvxlab/backend/problem.py
cvxlab/backend/set_table.py
cvxlab/backend/variable.py
cvxlab/log_exc/__init__.py
cvxlab/log_exc/exceptions.py
cvxlab/log_exc/logger.py
cvxlab/support/__init__.py
cvxlab/support/dotdict.py
cvxlab/support/file_manager.py
cvxlab/support/model_directory.py
cvxlab/support/sql_manager.py
cvxlab/support/util.py
cvxlab/support/util_constants.py
cvxlab/support/util_operators.py
cvxlab/support/util_text.py
cvxlab-1.0.1b1.dist-info/licenses/LICENSE
cvxlab-1.0.1b1.dist-info/METADATA
cvxlab-1.0.1b1.dist-info/WHEEL
cvxlab-1.0.1b1.dist-info/top_level.txt
cvxlab-1.0.1b1.dist-info/RECORD
