Metadata-Version: 2.4
Name: cvxlab
Version: 1.0.1b1
Summary: CVXlab - Open-source Python laboratory for convex algebraic modeling
Author-email: "Matteo V. Rocco" <matteovincenzo.rocco@polimi.it>
License: Apache-2.0
Project-URL: Homepage, https://github.com/cvxlab/cvxlab
Project-URL: Documentation, https://cvxlab.readthedocs.io
Project-URL: Repository, https://github.com/cvxlab/cvxlab
Project-URL: Issues, https://github.com/cvxlab/cvxlab/issues
Classifier: Development Status :: 4 - Beta
Classifier: Intended Audience :: Science/Research
Classifier: License :: OSI Approved :: Apache Software License
Classifier: Programming Language :: Python :: 3
Classifier: Programming Language :: Python :: 3.8
Classifier: Programming Language :: Python :: 3.9
Classifier: Programming Language :: Python :: 3.10
Classifier: Programming Language :: Python :: 3.11
Classifier: Topic :: Scientific/Engineering :: Mathematics
Requires-Python: >=3.8
License-File: LICENSE
Requires-Dist: numpy>=1.20.0
Requires-Dist: pandas>=1.3.0
Requires-Dist: scipy>=1.7.0
Requires-Dist: cvxpy>=1.7.3
Requires-Dist: openpyxl>=3.0.0
Requires-Dist: pyyaml>=5.4.0
Requires-Dist: dill>=0.3.4
Provides-Extra: dev
Requires-Dist: pytest>=6.2.0; extra == "dev"
Requires-Dist: pytest-cov>=2.12.0; extra == "dev"
Provides-Extra: docs
Requires-Dist: sphinx>=7.0; extra == "docs"
Requires-Dist: pydata-sphinx-theme; extra == "docs"
Requires-Dist: sphinx-autodoc-typehints; extra == "docs"
Requires-Dist: sphinxcontrib-mermaid; extra == "docs"
Requires-Dist: myst-nb>=1.0.0; extra == "docs"
Provides-Extra: solvers
Requires-Dist: gurobipy>=9.5.0; extra == "solvers"
Dynamic: license-file
